odoo/addons/ssi_outsource_work/README.rst
odoo/addons/ssi_outsource_work/__init__.py
odoo/addons/ssi_outsource_work/__manifest__.py
odoo/addons/ssi_outsource_work/menu.xml
odoo/addons/ssi_outsource_work/controllers/__init__.py
odoo/addons/ssi_outsource_work/controllers/portal.py
odoo/addons/ssi_outsource_work/data/approval_template_data.xml
odoo/addons/ssi_outsource_work/data/ir_sequence_data.xml
odoo/addons/ssi_outsource_work/data/policy_template_data.xml
odoo/addons/ssi_outsource_work/data/sequence_template_data.xml
odoo/addons/ssi_outsource_work/models/__init__.py
odoo/addons/ssi_outsource_work/models/ir_model.py
odoo/addons/ssi_outsource_work/models/mixin_outsource_work_object.py
odoo/addons/ssi_outsource_work/models/outsource_work.py
odoo/addons/ssi_outsource_work/models/outsource_work_outstanding.py
odoo/addons/ssi_outsource_work/models/outsource_work_outstanding_batch.py
odoo/addons/ssi_outsource_work/models/outsource_work_outstanding_batch_detail.py
odoo/addons/ssi_outsource_work/models/outsource_work_outstanding_tax.py
odoo/addons/ssi_outsource_work/models/outsource_work_outstanding_type.py
odoo/addons/ssi_outsource_work/models/outsource_work_type.py
odoo/addons/ssi_outsource_work/models/outsource_work_type_category.py
odoo/addons/ssi_outsource_work/security/ir.model.access.csv
odoo/addons/ssi_outsource_work/security/ir_module_category_data.xml
odoo/addons/ssi_outsource_work/security/ir_rule_data.xml
odoo/addons/ssi_outsource_work/security/res_group_data.xml
odoo/addons/ssi_outsource_work/static/description/icon.png
odoo/addons/ssi_outsource_work/templates/outsource_work_mixin_templates.xml
odoo/addons/ssi_outsource_work/views/ir_model_views.xml
odoo/addons/ssi_outsource_work/views/outsource_work_outstanding_batch_views.xml
odoo/addons/ssi_outsource_work/views/outsource_work_outstanding_portal_templates.xml
odoo/addons/ssi_outsource_work/views/outsource_work_outstanding_type_views.xml
odoo14_addon_ssi_outsource_work-14.0.1.14.0.dist-info/METADATA
odoo14_addon_ssi_outsource_work-14.0.1.14.0.dist-info/WHEEL
odoo14_addon_ssi_outsource_work-14.0.1.14.0.dist-info/top_level.txt
odoo14_addon_ssi_outsource_work-14.0.1.14.0.dist-info/RECORD
